azure/mgmt/alertsmanagement/__init__.py
azure/mgmt/alertsmanagement/_alerts_management_client.py
azure/mgmt/alertsmanagement/_configuration.py
azure/mgmt/alertsmanagement/_version.py
azure/mgmt/alertsmanagement/aio/__init__.py
azure/mgmt/alertsmanagement/aio/_alerts_management_client.py
azure/mgmt/alertsmanagement/aio/_configuration.py
azure/mgmt/alertsmanagement/aio/operations/__init__.py
azure/mgmt/alertsmanagement/aio/operations/_action_rules_operations.py
azure/mgmt/alertsmanagement/aio/operations/_alerts_operations.py
azure/mgmt/alertsmanagement/aio/operations/_operations.py
azure/mgmt/alertsmanagement/aio/operations/_smart_detector_alert_rules_operations.py
azure/mgmt/alertsmanagement/aio/operations/_smart_groups_operations.py
azure/mgmt/alertsmanagement/models/__init__.py
azure/mgmt/alertsmanagement/models/_alerts_management_client_enums.py
azure/mgmt/alertsmanagement/models/_models.py
azure/mgmt/alertsmanagement/models/_models_py3.py
azure/mgmt/alertsmanagement/operations/__init__.py
azure/mgmt/alertsmanagement/operations/_action_rules_operations.py
azure/mgmt/alertsmanagement/operations/_alerts_operations.py
azure/mgmt/alertsmanagement/operations/_operations.py
azure/mgmt/alertsmanagement/operations/_smart_detector_alert_rules_operations.py
azure/mgmt/alertsmanagement/operations/_smart_groups_operations.py
azure_mgmt_alertsmanagement-1.0.0.dist-info/METADATA
azure_mgmt_alertsmanagement-1.0.0.dist-info/WHEEL
azure_mgmt_alertsmanagement-1.0.0.dist-info/top_level.txt
azure_mgmt_alertsmanagement-1.0.0.dist-info/RECORD
